kafka_temporal_mapper/client/__init__.py
kafka_temporal_mapper/client/client.py
kafka_temporal_mapper/common/config.py
kafka_temporal_mapper/common/types.py
kafka_temporal_mapper_client-0.1.1.dist-info/LICENSE
kafka_temporal_mapper_client-0.1.1.dist-info/WHEEL
kafka_temporal_mapper_client-0.1.1.dist-info/METADATA
kafka_temporal_mapper_client-0.1.1.dist-info/RECORD
