Metadata-Version: 2.1
Name: kafka-temporal-mapper-client
Version: 0.1.1
Summary: A client library to send subscribe and notify workflow events to the kafka-temporal-mapper server.
License: AGPL-3.0-only
Author: gtato
Requires-Python: >=3.8,<4.0
Classifier: License :: OSI Approved :: GNU Affero General Public License v3
Classifier: Programming Language :: Python :: 3
Classifier: Programming Language :: Python :: 3.8
Classifier: Programming Language :: Python :: 3.9
Classifier: Programming Language :: Python :: 3.10
Classifier: Programming Language :: Python :: 3.11
Requires-Dist: dacite (>=1.7.0,<2.0.0)
Requires-Dist: dataclasses-json (>=0.5.7,<0.6.0)
Requires-Dist: kafka-python (>=2.0.2,<3.0.0)
Project-URL: source, https://github.com/canonical/kafka_temporal_mapper
